{
    "directories": [
        {
            "name": "smevSender",
            "values":
            {
                "382801": "Региональный портал государственных и муниципальных услуг Пензенской области",
                "PGUR01581": "Портал государственных и муниципальных услуг Пензенской области",
                "PNZR01581": "Управление информатизации Пензенской области",
                "IPGU01581": "Единый портал государственных услуг (gosuslugi.ru)",
                "IPGU01001": "Единый портал государственных услуг (Тест)"
            }

        },
        {
            "name": "smevResultType",
            "values":
            {
                "4": "Отказано",
                "3": "Исполнено"
            }

        }
    ]
}
